netbox_passhup_plugin/__init__.py
netbox_passhup_plugin/utilities/__init__.py
netbox_passhup_plugin-0.0.1.dist-info/LICENSE
netbox_passhup_plugin-0.0.1.dist-info/METADATA
netbox_passhup_plugin-0.0.1.dist-info/WHEEL
netbox_passhup_plugin-0.0.1.dist-info/top_level.txt
netbox_passhup_plugin-0.0.1.dist-info/RECORD
