Metadata-Version: 2.1
Name: netbox-passhup-plugin
Version: 0.0.1
Summary: Manage Passhup Netbox distribution initialization and behaviours.
Author-email: Vincent Simonin <vincent@saashup.com>
Project-URL: Homepage, https://github.com/SaaShup/netbox-passhup-plugin
Project-URL: Bug Tracker, https://github.com/SaaShup/netbox-passhup-plugin/issues
Keywords: netbox,netbox-plugin,passhup
Classifier: Programming Language :: Python :: 3
Requires-Python: >=3.11
License-File: LICENSE
